CustomConsole/Alias.py
CustomConsole/Color.py
CustomConsole/Highlights.py
CustomConsole/__init__.py
CustomConsole-1.1.0.dist-info/LICENSE
CustomConsole-1.1.0.dist-info/METADATA
CustomConsole-1.1.0.dist-info/WHEEL
CustomConsole-1.1.0.dist-info/top_level.txt
CustomConsole-1.1.0.dist-info/RECORD
