Metadata-Version: 2.1
Name: CustomConsole
Version: 1.1.0
Summary: To make Console better
Author: Mohd Zaid
Author-email: MohdZaid <zaid2092005@gmail.com>
Project-URL: Homepage, https://github.com/MohdZaid5/CustomConsole/tree/master
Project-URL: Bug Tracker, https://github.com/MohdZaid5/CustomConsole/issues
Classifier: Programming Language :: Python :: 3
Classifier: License :: OSI Approved :: MIT License
Classifier: Operating System :: OS Independent
Requires-Python: >=3.0
License-File: LICENSE
